econcausal/__init__.py
econcausal/client.py
econcausal/causal/discovery.py
econcausal/data/catalog.py
econcausal/optimization/optimizer.py
econcausal/simulation/abm.py
econcausal-0.2.0.dist-info/METADATA
econcausal-0.2.0.dist-info/WHEEL
econcausal-0.2.0.dist-info/top_level.txt
econcausal-0.2.0.dist-info/RECORD
