Metadata-Version: 2.4
Name: econcausal
Version: 0.2.0
Summary: SDK for EconCausalAI - Causal Discovery and Economic Simulation with Bootstrap Uncertainty
Author-email: Karthik <karthik@econcausal.ai>
Project-URL: Homepage, https://github.com/econcausal/econcausal-sdk
Keywords: causal-inference,economics,agent-based-modeling,policy-analysis,simulation
Classifier: Development Status :: 4 - Beta
Classifier: Intended Audience :: Science/Research
Classifier: Topic :: Scientific/Engineering :: Artificial Intelligence
Classifier: Programming Language :: Python :: 3
Classifier: Programming Language :: Python :: 3.8
Classifier: Programming Language :: Python :: 3.9
Classifier: Programming Language :: Python :: 3.10
Classifier: Programming Language :: Python :: 3.11
Classifier: License :: OSI Approved :: MIT License
Classifier: Operating System :: OS Independent
Requires-Python: >=3.8
Requires-Dist: requests>=2.28.0
Requires-Dist: pandas>=1.5.0
Requires-Dist: numpy>=1.24.0
